ambient_api/__init__.py
ambient_api/ambientapi.py
ambient_api/settings.py
ambient_api-1.5.6.dist-info/LICENSE
ambient_api-1.5.6.dist-info/METADATA
ambient_api-1.5.6.dist-info/WHEEL
ambient_api-1.5.6.dist-info/top_level.txt
ambient_api-1.5.6.dist-info/RECORD
