Metadata-Version: 2.1
Name: ambient-api
Version: 1.5.6
Summary: A Python class for accessing the Ambient Weather API.
Home-page: https://github.com/avryhof/ambient_api
Author: Amos Vryhof
Author-email: amos@vryhofresearch.com
License: MIT
Platform: UNKNOWN
Classifier: Development Status :: 5 - Production/Stable
Classifier: Intended Audience :: Developers
Classifier: License :: OSI Approved :: MIT License
Classifier: Programming Language :: Python :: 3
License-File: LICENSE
Requires-Dist: requests
Requires-Dist: urllib3
